{
  "audio": [
    {
      "id": 0,
      "name": "Get away from me, freak!",
      "file": "get_away_from_me_freak.mp3"
    },
    {
      "id": 1,
      "name": "Hanya?",
      "file": "hanya.mp3"
    },
    {
      "id": 2,
      "name": "I hope you die!",
      "file": "i_hope_you_die.mp3"
    },
    {
      "id": 3,
      "name": "That's not fair!",
      "file": "thats_not_fair.mp3"
    },
    {
      "id": 4,
      "name": "Wooow~",
      "file": "wooow.mp3"
    },
    {
      "id": 5,
      "name": "Oh, this mother-beeper!",
      "file": "oh_this_mother_beeper.mp3"
    },
    {
      "id": 6,
      "name": "That's lewd!",
      "file": "thats_lewd.mp3"
    },
    {
      "id": 7,
      "name": "Dangit! Beep you!",
      "file": "dangit_beep_you.mp3"
    },
    {
      "id": 8,
      "name": "WHAT?!?!",
      "file": "what.mp3"
    },
    {
      "id": 9,
      "name": "Ugh, I'm in jail! Dangit!",
      "file": "im_in_jail_dangit.mp3"
    },
    {
      "id": 10,
      "name": "*PANIC NOISES*",
      "file": "panic.mp3"
    },
    {
      "id": 11,
      "name": "I looove you!",
      "file": "i_love_you.mp3"
    },
    {
      "id": 12,
      "name": "Good night~",
      "file": "good_night.mp3"
    },
    {
      "id": 13,
      "name": "I love casting spells!",
      "file": "i_love_casting_spells.mp3"
    },
    {
      "id": 14,
      "name": "A-Ahh! Bweh...",
      "file": "ahh_bweh.mp3"
    },
    {
      "id": 15,
      "name": "AHHHHH!!",
      "file": "scream.mp3"
    },
    {
      "id": 16,
      "name": "Disgusting!",
      "file": "disgusting.mp3"
    },
    {
      "id": 17,
      "name": "Say please~",
      "file": "say_please.mp3"
    },
    {
      "id": 18,
      "name": "What if you're not real?",
      "file": "what_if_youre_not_real.mp3"
    },
    {
      "id": 19,
      "name": "I don't wanna touch grass anymore! Help!",
      "file": "i_dont_wanna_touch_grass_anymore_help.mp3"
    },
    {
      "id": 20,
      "name": "Meow~",
      "file": "meow.mp3"
    },
    {
      "id": 21,
      "name": "Oohhh!",
      "file": "ooh.mp3"
    },
    {
      "id": 22,
      "name": "Everybody, calm down!",
      "file": "everybody_calm_down.mp3"
    },
    {
      "id": 23,
      "name": "Yay! Let's go, mother-beepers!",
      "file": "lets_go_mother_beepers.mp3"
    }
  ]
}
